LICENSE.txt
MANIFEST.in
README.md
setup.cfg
setup.py
examples/test1_emotion_analysis.py
examples/test1_emotion_analysis2.py
examples/test2_mfcc.py
examples/test3_volume.py
src/speech_features_kit/__init__.py
src/speech_features_kit.egg-info/PKG-INFO
src/speech_features_kit.egg-info/SOURCES.txt
src/speech_features_kit.egg-info/dependency_links.txt
src/speech_features_kit.egg-info/requires.txt
src/speech_features_kit.egg-info/top_level.txt
src/speech_features_kit/Emotion/__init__.py
src/speech_features_kit/Emotion/speech_toolkit.py
src/speech_features_kit/Emotion/__pycache__/__init__.cpython-36.pyc
src/speech_features_kit/Emotion/__pycache__/speech_toolkit.cpython-36.pyc
src/speech_features_kit/Emotion/models/mfcc_model_para_dict.pkl
src/speech_features_kit/Emotion/models/speech_mfcc_model.h5
src/speech_features_kit/MFCC/MFCC.py
src/speech_features_kit/MFCC/__init__.py
src/speech_features_kit/MFCC/sigproc.py
src/speech_features_kit/MFCC/__pycache__/MFCC.cpython-36.pyc
src/speech_features_kit/MFCC/__pycache__/__init__.cpython-36.pyc
src/speech_features_kit/MFCC/__pycache__/sigproc.cpython-36.pyc
src/speech_features_kit/Volume/Volume.py
src/speech_features_kit/Volume/__init__.py
src/speech_features_kit/Volume/__pycache__/Volume.cpython-36.pyc
src/speech_features_kit/Volume/__pycache__/__init__.cpython-36.pyc
src/speech_features_kit/__pycache__/__init__.cpython-36.pyc